{
  "_class": "group",
  "booleanOperation": 0,
  "clippingMaskMode": 0,
  "do_objectID": "D3171670-124C-4FDA-9520-F7665051E0D9",
  "exportOptions": {
    "_class": "exportOptions",
    "do_objectID": "D038436B-2A19-41AB-B9FD-22672D2FF65B",
    "exportFormats": [
    ],
    "includedLayerIds": [
    ],
    "layerOptions": 0,
    "shouldTrim": false
  },
  "frame": {
    "_class": "rect",
    "constrainProportions": false,
    "do_objectID": "53979E94-0304-4BEE-9548-0F0172F8481D",
    "height": 867.6,
    "width": 1270.8,
    "x": 273.6,
    "y": 27
  },
  "hasClickThrough": false,
  "hasClippingMask": false,
  "isFixedToViewport": false,
  "isFlippedHorizontal": false,
  "isFlippedVertical": false,
  "isLocked": false,
  "isVisible": false,
  "layerListExpandedType": 0,
  "layers": [
    {
      "class": "shapePath",
      "id": "7BB23E52-A0DA-4A2E-9E74-6574238B94B0"
    },
    {
      "class": "shapePath",
      "id": "865FBA1E-23BB-41CD-B676-7560EFA9ED75"
    }
  ],
  "name": "Shadow",
  "nameIsFixed": true,
  "resizingConstraint": 63,
  "resizingType": 0,
  "rotation": 0,
  "shouldBreakMaskChain": false,
  "style": {
    "_class": "style",
    "blur": {
      "_class": "blur",
      "center": "{0.5, 0.5}",
      "do_objectID": "0FF48B6B-E6F6-4DBB-B52D-DE9E63828F34",
      "isEnabled": false,
      "motionAngle": 0,
      "radius": 6,
      "saturation": 1,
      "type": 0
    },
    "do_objectID": "D26E110C-6412-4613-B459-25347FBECDA2",
    "endMarkerType": 0,
    "miterLimit": 10,
    "startMarkerType": 0,
    "windingRule": 1
  }
}