{
  "_class": "shapeGroup",
  "clippingMaskMode": 0,
  "do_objectID": "35F184F9-A461-4A04-978A-4BA60F9EAF8B",
  "exportOptions": {
    "_class": "exportOptions",
    "exportFormats": [
    ],
    "includedLayerIds": [
    ],
    "layerOptions": 0,
    "shouldTrim": false
  },
  "frame": {
    "_class": "rect",
    "constrainProportions": false,
    "height": 22,
    "width": 4,
    "x": 18,
    "y": 75
  },
  "hasClickThrough": false,
  "hasClippingMask": false,
  "isFlippedHorizontal": false,
  "isFlippedVertical": false,
  "isLocked": false,
  "isVisible": true,
  "layerListExpandedType": 0,
  "layers": [
    {
      "class": "rectangle",
      "id": "BD5B0CEE-3BDC-4104-B3E5-2EB8AF262D12"
    }
  ],
  "name": "Rectangle 8",
  "nameIsFixed": false,
  "resizingConstraint": 63,
  "resizingType": 0,
  "rotation": 0,
  "shouldBreakMaskChain": false,
  "style": {
    "sharedObjectID": "B5E140AD-7AC8-4293-8071-10D6B60C066C"
  },
  "windingRule": 1
}