{
  "_class": "group",
  "do_objectID": "9B7670B2-6A39-4921-8154-E27E5B61FBB2",
  "exportOptions": {
    "_class": "exportOptions",
    "exportFormats": [
    ],
    "includedLayerIds": [
    ],
    "layerOptions": 0,
    "shouldTrim": false
  },
  "frame": {
    "_class": "rect",
    "constrainProportions": false,
    "height": 81,
    "width": 346,
    "x": 14,
    "y": 641
  },
  "hasClickThrough": false,
  "isFlippedHorizontal": false,
  "isFlippedVertical": false,
  "isLocked": false,
  "isVisible": true,
  "layerListExpandedType": 0,
  "layers": [
    {
      "class": "group",
      "id": "71499D1B-BC69-4618-B990-F25AC0F737B0"
    },
    {
      "class": "group",
      "id": "4424125F-28CE-492E-88C0-ECC13F71E391"
    },
    {
      "class": "text",
      "id": "1F3C1EE7-35EC-4C6F-8610-E7BE6F9806BB"
    },
    {
      "class": "text",
      "id": "6BEF2E34-6FA7-4274-A10C-7C218E5BEAD6"
    },
    {
      "class": "text",
      "id": "208D1A0E-9967-412F-8B6C-2749598837AB"
    },
    {
      "class": "group",
      "id": "13266654-2FDD-414C-9740-8605A9F75F12"
    },
    {
      "class": "group",
      "id": "D4DE46D5-67B9-4836-9513-35D8201FBC05"
    }
  ],
  "name": "单条列表 copy 2",
  "nameIsFixed": true,
  "resizingConstraint": 63,
  "resizingType": 0,
  "rotation": 0,
  "shouldBreakMaskChain": false,
  "style": {
    "_class": "style",
    "endDecorationType": 0,
    "miterLimit": 10,
    "startDecorationType": 0
  }
}