{
  "_class": "shapeGroup",
  "clippingMaskMode": 0,
  "do_objectID": "8F11638C-89E9-49AF-9480-0092F61641AB",
  "exportOptions": {
    "_class": "exportOptions",
    "exportFormats": [
    ],
    "includedLayerIds": [
    ],
    "layerOptions": 0,
    "shouldTrim": false
  },
  "frame": {
    "_class": "rect",
    "constrainProportions": false,
    "height": 8,
    "width": 16,
    "x": 324,
    "y": 86
  },
  "hasClickThrough": false,
  "hasClippingMask": false,
  "isFlippedHorizontal": false,
  "isFlippedVertical": true,
  "isLocked": false,
  "isVisible": true,
  "layerListExpandedType": 0,
  "layers": [
    {
      "class": "triangle",
      "id": "9F97C5F1-9F0E-4390-88BF-5A3759F3083B"
    }
  ],
  "name": "Triangle 2",
  "nameIsFixed": false,
  "resizingConstraint": 63,
  "resizingType": 0,
  "rotation": 0,
  "shouldBreakMaskChain": false,
  "style": {
    "sharedObjectID": "E7DD20D0-D4D2-44B5-BEB4-676886C35CCD"
  },
  "windingRule": 1
}