{
  "_class": "group",
  "do_objectID": "5C49E705-588B-43AC-8A97-4AE2F3351022",
  "exportOptions": {
    "_class": "exportOptions",
    "exportFormats": [
    ],
    "includedLayerIds": [
    ],
    "layerOptions": 0,
    "shouldTrim": false
  },
  "frame": {
    "_class": "rect",
    "constrainProportions": false,
    "height": 50,
    "width": 340,
    "x": 19,
    "y": 614
  },
  "hasClickThrough": false,
  "isFlippedHorizontal": false,
  "isFlippedVertical": false,
  "isLocked": false,
  "isVisible": true,
  "layerListExpandedType": 0,
  "layers": [
    {
      "class": "shapeGroup",
      "id": "3FF024CF-B77F-49A8-8C67-E3F9FFE965A4"
    },
    {
      "class": "group",
      "id": "D2650891-334E-433F-B983-2571F606DFA1"
    }
  ],
  "name": "扫描设备按钮",
  "nameIsFixed": true,
  "resizingConstraint": 63,
  "resizingType": 0,
  "rotation": 0,
  "shouldBreakMaskChain": false,
  "style": {
    "_class": "style",
    "endDecorationType": 0,
    "miterLimit": 10,
    "startDecorationType": 0
  }
}