{
  "_class": "shapeGroup",
  "clippingMaskMode": 0,
  "do_objectID": "A0BD9372-EAAF-4E8E-8CCC-31595C3C67F6",
  "exportOptions": {
    "_class": "exportOptions",
    "exportFormats": [
    ],
    "includedLayerIds": [
    ],
    "layerOptions": 0,
    "shouldTrim": false
  },
  "frame": {
    "_class": "rect",
    "constrainProportions": false,
    "height": 21.98429062108516,
    "width": 25.08039462574511,
    "x": 0.009906377599236293,
    "y": 0.009234462526933385
  },
  "hasClickThrough": false,
  "hasClippingMask": false,
  "isFlippedHorizontal": false,
  "isFlippedVertical": false,
  "isLocked": false,
  "isVisible": true,
  "layerListExpandedType": 0,
  "layers": [
    {
      "class": "shapePath",
      "id": "ADE417C7-492E-4972-A938-B860F7284F0D"
    },
    {
      "class": "shapePath",
      "id": "534193B5-E0CA-4060-BB15-6A09AF4DAE85"
    },
    {
      "class": "shapePath",
      "id": "6CAEB350-CF25-4A91-9413-BF362AB91E45"
    }
  ],
  "name": "Shape",
  "nameIsFixed": false,
  "resizingConstraint": 63,
  "resizingType": 0,
  "rotation": 0,
  "shouldBreakMaskChain": false,
  "style": {
    "_class": "style",
    "endDecorationType": 0,
    "fills": [
      {
        "_class": "fill",
        "color": {
          "_class": "color",
          "alpha": 1,
          "blue": 0.8823529411764706,
          "green": 0.8431372549019608,
          "red": 0.8117647058823529
        },
        "fillType": 0,
        "isEnabled": true,
        "noiseIndex": 0,
        "noiseIntensity": 0,
        "patternFillType": 1,
        "patternTileScale": 1
      }
    ],
    "miterLimit": 10,
    "startDecorationType": 0
  },
  "windingRule": 0
}