{
  "_class": "shapePath",
  "booleanOperation": -1,
  "do_objectID": "D8330EDD-3C32-426B-90CF-8FC64A787077",
  "edited": true,
  "exportOptions": {
    "_class": "exportOptions",
    "exportFormats": [
    ],
    "includedLayerIds": [
    ],
    "layerOptions": 0,
    "shouldTrim": false
  },
  "frame": {
    "_class": "rect",
    "constrainProportions": false,
    "height": 2,
    "width": 2,
    "x": 0,
    "y": 0
  },
  "isFlippedHorizontal": false,
  "isFlippedVertical": false,
  "isLocked": false,
  "isVisible": true,
  "layerListExpandedType": 0,
  "name": "Path",
  "nameIsFixed": false,
  "path": {
    "_class": "path",
    "isClosed": true,
    "pointRadiusBehaviour": 0,
    "points": [
      {
        "_class": "curvePoint",
        "cornerRadius": 0,
        "curveFrom": "{1, 0.77620858229223244}",
        "curveMode": 2,
        "curveTo": "{1, 0.22380787780027314}",
        "hasCurveFrom": true,
        "hasCurveTo": true,
        "point": "{1, 0.5}"
      },
      {
        "_class": "curvePoint",
        "cornerRadius": 0,
        "curveFrom": "{0.22379510139583877, 1}",
        "curveMode": 2,
        "curveTo": "{0.7762048986041612, 1}",
        "hasCurveFrom": true,
        "hasCurveTo": true,
        "point": "{0.5, 1}"
      },
      {
        "_class": "curvePoint",
        "cornerRadius": 0,
        "curveFrom": "{0, 0.22379141770776734}",
        "curveMode": 2,
        "curveTo": "{0, 0.77620858229223244}",
        "hasCurveFrom": true,
        "hasCurveTo": true,
        "point": "{0, 0.5}"
      },
      {
        "_class": "curvePoint",
        "cornerRadius": 0,
        "curveFrom": "{0.7762048986041612, 0}",
        "curveMode": 2,
        "curveTo": "{0.22379510139583877, 0}",
        "hasCurveFrom": true,
        "hasCurveTo": true,
        "point": "{0.5, 0}"
      }
    ]
  },
  "resizingConstraint": 63,
  "resizingType": 0,
  "rotation": 0,
  "shouldBreakMaskChain": false
}