{
  "_class": "group",
  "do_objectID": "774C0C6B-8697-41E9-8730-344D8EABC4A4",
  "exportOptions": {
    "_class": "exportOptions",
    "exportFormats": [
    ],
    "includedLayerIds": [
    ],
    "layerOptions": 0,
    "shouldTrim": false
  },
  "frame": {
    "_class": "rect",
    "constrainProportions": false,
    "height": 15,
    "width": 61,
    "x": 294,
    "y": 3
  },
  "hasClickThrough": false,
  "isFlippedHorizontal": false,
  "isFlippedVertical": false,
  "isLocked": false,
  "isVisible": true,
  "layerListExpandedType": 0,
  "layers": [
    {
      "class": "shapeGroup",
      "id": "905697FE-B8CC-43F3-862F-C08AD97619C3"
    },
    {
      "class": "text",
      "id": "8781A137-38BB-41B1-A0A7-473821D1681B"
    }
  ],
  "name": "Pin Right",
  "nameIsFixed": true,
  "resizingConstraint": 44,
  "resizingType": 1,
  "rotation": 0,
  "shouldBreakMaskChain": false,
  "style": {
    "_class": "style",
    "endDecorationType": 0,
    "miterLimit": 10,
    "startDecorationType": 0
  }
}