{
  "_class": "shapePath",
  "booleanOperation": -1,
  "do_objectID": "16B3C714-813B-46AC-88F3-D2D31B09D24F",
  "edited": true,
  "exportOptions": {
    "_class": "exportOptions",
    "exportFormats": [
    ],
    "includedLayerIds": [
    ],
    "layerOptions": 0,
    "shouldTrim": false
  },
  "frame": {
    "_class": "rect",
    "constrainProportions": false,
    "height": 49,
    "width": 3,
    "x": 0,
    "y": 0
  },
  "isFlippedHorizontal": false,
  "isFlippedVertical": false,
  "isLocked": false,
  "isVisible": true,
  "layerListExpandedType": 0,
  "name": "Path",
  "nameIsFixed": false,
  "path": {
    "_class": "path",
    "isClosed": false,
    "pointRadiusBehaviour": 0,
    "points": [
      {
        "_class": "curvePoint",
        "cornerRadius": 0,
        "curveFrom": "{0.66666666666666663, -3.4694469519536142e-18}",
        "curveMode": 1,
        "curveTo": "{0.66666666666666663, -3.4694469519536142e-18}",
        "hasCurveFrom": false,
        "hasCurveTo": false,
        "point": "{0.500000000000001, 0.01020408163265306}"
      },
      {
        "_class": "curvePoint",
        "cornerRadius": 0,
        "curveFrom": "{1, 0.02040816326530611}",
        "curveMode": 1,
        "curveTo": "{1, 0.02040816326530611}",
        "hasCurveFrom": false,
        "hasCurveTo": false,
        "point": "{0.500000000000001, 0.98979591836734693}"
      }
    ]
  },
  "resizingConstraint": 63,
  "resizingType": 0,
  "rotation": 0,
  "shouldBreakMaskChain": false
}