{
  "_class": "bitmap",
  "booleanOperation": 0,
  "clippingMask": "{{0, 0}, {1, 1}}",
  "clippingMaskMode": 0,
  "do_objectID": "B3B46562-DF7D-4305-9531-BAEFFFAEB7DC",
  "exportOptions": {
    "_class": "exportOptions",
    "do_objectID": "5FB3F685-9404-4C3A-8FD7-B6FC87A2006E",
    "exportFormats": [
    ],
    "includedLayerIds": [
    ],
    "layerOptions": 0,
    "shouldTrim": false
  },
  "fillReplacesImage": false,
  "frame": {
    "_class": "rect",
    "constrainProportions": true,
    "do_objectID": "27B04747-6D80-4054-B195-32B99C0268B2",
    "height": 460,
    "width": 654.5,
    "x": -0.5,
    "y": -0.25
  },
  "hasClippingMask": false,
  "image": {
    "_class": "MSJSONFileReference",
    "_ref": "images/86f8e5b3cc41c9031d6d8f9eb2fea8b0d419f1ab.png",
    "_ref_class": "MSImageData"
  },
  "intendedDPI": 0,
  "isFixedToViewport": false,
  "isFlippedHorizontal": false,
  "isFlippedVertical": false,
  "isLocked": false,
  "isVisible": true,
  "layerListExpandedType": 0,
  "name": "Overlay",
  "nameIsFixed": true,
  "resizingConstraint": 63,
  "resizingType": 0,
  "rotation": 0,
  "shouldBreakMaskChain": false,
  "style": {
    "_class": "style",
    "blur": {
      "_class": "blur",
      "center": "{0.5, 0.5}",
      "do_objectID": "B680F8FB-9941-404E-8383-B18BD7707B63",
      "isEnabled": false,
      "motionAngle": 0,
      "radius": 2.5,
      "saturation": 1,
      "type": 0
    },
    "contextSettings": {
      "_class": "graphicsContextSettings",
      "blendMode": 7,
      "do_objectID": "ED366224-8C40-42C8-9800-4430BAC26A03",
      "opacity": 1
    },
    "do_objectID": "67B19AF7-1A24-4AB0-AC3E-BFC19C040B2B",
    "endMarkerType": 0,
    "miterLimit": 10,
    "startMarkerType": 0,
    "windingRule": 1
  }
}