{
  "_class": "group",
  "do_objectID": "5E81A7FB-CC6C-42D0-A402-7D3DD3F76044",
  "exportOptions": {
    "_class": "exportOptions",
    "exportFormats": [
    ],
    "includedLayerIds": [
    ],
    "layerOptions": 0,
    "shouldTrim": false
  },
  "frame": {
    "_class": "rect",
    "constrainProportions": false,
    "height": 15,
    "width": 61,
    "x": 309,
    "y": 3
  },
  "hasClickThrough": false,
  "isFlippedHorizontal": false,
  "isFlippedVertical": false,
  "isLocked": false,
  "isVisible": true,
  "layerListExpandedType": 0,
  "layers": [
    {
      "class": "shapeGroup",
      "id": "42E0D0C2-89A1-4D90-883C-D10D8D1C650B"
    },
    {
      "class": "text",
      "id": "CC3BEF9F-3A38-49E0-947A-2A8BDBDDEE54"
    }
  ],
  "name": "Pin Right",
  "nameIsFixed": true,
  "resizingConstraint": 44,
  "resizingType": 1,
  "rotation": 0,
  "shouldBreakMaskChain": false,
  "style": {
    "_class": "style",
    "endDecorationType": 0,
    "miterLimit": 10,
    "startDecorationType": 0
  }
}